steadfast/__init__.py
steadfast/archive.py
steadfast/common.py
steadfast/core.py
steadfast/decorators.py
steadfast/identifiers.py
steadfast/inspect.py
steadfast/operators.py
steadfast/priority_queue.py
steadfast/test_core.py
steadfast/test_example.py
steadfast/toposort.py
steadfast/types.py
steadfast-1.0.1.dist-info/AUTHORS.txt
steadfast-1.0.1.dist-info/LICENSE.txt
steadfast-1.0.1.dist-info/METADATA
steadfast-1.0.1.dist-info/WHEEL
steadfast-1.0.1.dist-info/top_level.txt
steadfast-1.0.1.dist-info/RECORD
