Metadata-Version: 2.1
Name: steadfast
Version: 1.0.1
Summary: Utilities for object serialization.
Home-page: https://github.com/high-dimensional/steadfast
Author: High Dimensional Neurology Group, UCL
Author-email: pypi@highdimensional.net
License: BSD-3-Clause
Platform: any
Classifier: Framework :: Django
Classifier: Framework :: Wagtail
Classifier: Programming Language :: Python :: 3
Classifier: Programming Language :: Python :: 3.9
Classifier: License :: OSI Approved :: BSD License
Classifier: Operating System :: OS Independent
Requires-Python: ~=3.9
License-File: LICENSE.txt
License-File: AUTHORS.txt
